cloudwise/__init__.py
cloudwise/gke/__init__.py
cloudwise/gke/gke.py
cloudwise/gke/gke_commandline.py
cloudwise/utils/__init__.py
cloudwise/utils/common.py
cloudwise/utils/user_input.py
cloudwise-0.1.1.dist-info/METADATA
cloudwise-0.1.1.dist-info/WHEEL
cloudwise-0.1.1.dist-info/entry_points.txt
cloudwise-0.1.1.dist-info/top_level.txt
cloudwise-0.1.1.dist-info/RECORD
