Metadata-Version: 2.1
Name: cloudwise
Version: 0.1.1
Summary: Set up a Kubernetes cluster for distributed AI research
Home-page: http://github.com/SurrealAI/cloudwise
Author: Surreal AI
License: GPLv3
Keywords: machine learning,cloud computing,distributed computing,terraform,kubernetes
Platform: UNKNOWN
Classifier: Development Status :: 4 - Beta
Classifier: Environment :: Console
Classifier: Programming Language :: Python :: 3
Requires-Python: >=3.5
